uml_generator/__init__.py
uml_generator/main.py
uml_generator/converters/__init__.py
uml_generator/converters/class_converter.py
uml_generator/converters/relation_converter.py
uml_generator/core/__init__.py
uml_generator/core/diagram_converter.py
uml_generator/core/diagram_drawer.py
uml_generator/core/project_analyzer.py
uml_generator/models/__init__.py
uml_generator/models/uml_attribute.py
uml_generator/models/uml_class.py
uml_generator/models/uml_diagram.py
uml_generator/models/uml_method.py
uml_generator/models/uml_parameter.py
uml_generator/models/uml_relation.py
uml_generator/parsers/__init__.py
uml_generator/parsers/base_parser.py
uml_generator/parsers/java_parser.py
uml_generator/types/__init__.py
uml_generator/types/languages.py
uml_generator/types/relations.py
uml_generator-4.1.6.dist-info/LICENSE
uml_generator-4.1.6.dist-info/METADATA
uml_generator-4.1.6.dist-info/WHEEL
uml_generator-4.1.6.dist-info/entry_points.txt
uml_generator-4.1.6.dist-info/top_level.txt
uml_generator-4.1.6.dist-info/RECORD
