Metadata-Version: 2.1
Name: uml-generator
Version: 4.1.6
Summary: A tool to generate UML diagrams from project files.
Home-page: https://github.com/SIIR3X/python-uml-generator
Author: SIIR3X
Author-email: siir3xs@gmail.com
Classifier: Programming Language :: Python :: 3
Classifier: License :: OSI Approved :: MIT License
Classifier: Operating System :: OS Independent
Requires-Python: >=3.6
License-File: LICENSE
Requires-Dist: plantuml==0.3.0
